cssstyle2dict/__init__.py
cssstyle2dict/cssstyle2dict.py
cssstyle2dict-0.0.1.dist-info/LICENSE
cssstyle2dict-0.0.1.dist-info/METADATA
cssstyle2dict-0.0.1.dist-info/WHEEL
cssstyle2dict-0.0.1.dist-info/top_level.txt
cssstyle2dict-0.0.1.dist-info/RECORD
