Metadata-Version: 2.1
Name: cssstyle2dict
Version: 0.0.1
Summary: css style to dict
Home-page: https://github.com/jin10086/cssstyle2dict
Author: Gaojin
Author-email: igaojin@qq.com
License: UNKNOWN
Platform: UNKNOWN
Classifier: Programming Language :: Python
Classifier: License :: OSI Approved :: MIT License
Classifier: Operating System :: OS Independent
Requires-Dist: cssutils
